tf_noisy_image_dataset/__init__.py
tf_noisy_image_dataset/dataset.py
tf_noisy_image_dataset/noise.py
tf_noisy_image_dataset-0.2.1.dist-info/METADATA
tf_noisy_image_dataset-0.2.1.dist-info/WHEEL
tf_noisy_image_dataset-0.2.1.dist-info/top_level.txt
tf_noisy_image_dataset-0.2.1.dist-info/RECORD
