Metadata-Version: 2.1
Name: tf-noisy-image-dataset
Version: 0.2.1
Summary: Datasets for noisy images in the tf.data API.
Home-page: https://github.com/zaccharieramzi/tf-noisy-image-dataset
Author: Zaccharie Ramzi
Author-email: zaccharie.ramzi@gmail.com
License: UNKNOWN
Platform: UNKNOWN
Classifier: Programming Language :: Python :: 3
Classifier: License :: OSI Approved :: MIT License
Classifier: Operating System :: OS Independent
Requires-Python: >=3.6
Requires-Dist: tensorflow
